spherical_harmonics/__init__.py
spherical_harmonics/fundamental_set.py
spherical_harmonics/gegenbauer_polynomial.py
spherical_harmonics/jax.py
spherical_harmonics/plotting.py
spherical_harmonics/spherical_harmonics.py
spherical_harmonics/tensorflow.py
spherical_harmonics/torch.py
spherical_harmonics/utils.py
spherical_harmonics/fundamental_system/__init__.py
spherical_harmonics/fundamental_system/fs_10D.npz
spherical_harmonics/fundamental_system/fs_11D.npz
spherical_harmonics/fundamental_system/fs_12D.npz
spherical_harmonics/fundamental_system/fs_13D.npz
spherical_harmonics/fundamental_system/fs_14D.npz
spherical_harmonics/fundamental_system/fs_15D.npz
spherical_harmonics/fundamental_system/fs_16D.npz
spherical_harmonics/fundamental_system/fs_17D.npz
spherical_harmonics/fundamental_system/fs_18D.npz
spherical_harmonics/fundamental_system/fs_19D.npz
spherical_harmonics/fundamental_system/fs_20D.npz
spherical_harmonics/fundamental_system/fs_3D.npz
spherical_harmonics/fundamental_system/fs_4D.npz
spherical_harmonics/fundamental_system/fs_5D.npz
spherical_harmonics/fundamental_system/fs_6D.npz
spherical_harmonics/fundamental_system/fs_7D.npz
spherical_harmonics/fundamental_system/fs_8D.npz
spherical_harmonics/fundamental_system/fs_9D.npz
spherical_harmonics/lab_extras/__init__.py
spherical_harmonics/lab_extras/extras.py
spherical_harmonics/lab_extras/jax/__init__.py
spherical_harmonics/lab_extras/jax/extras.py
spherical_harmonics/lab_extras/numpy/__init__.py
spherical_harmonics/lab_extras/numpy/extras.py
spherical_harmonics/lab_extras/tensorflow/__init__.py
spherical_harmonics/lab_extras/tensorflow/extras.py
spherical_harmonics/lab_extras/torch/__init__.py
spherical_harmonics/lab_extras/torch/extras.py
spherical_harmonics_basis-0.0.2.dist-info/LICENSE
spherical_harmonics_basis-0.0.2.dist-info/WHEEL
spherical_harmonics_basis-0.0.2.dist-info/METADATA
spherical_harmonics_basis-0.0.2.dist-info/RECORD
