Metadata-Version: 2.1
Name: spherical-harmonics-basis
Version: 0.0.2
Summary: Python Implementation of Spherical harmonics in dimension >= 3
Author-email: Vincent Dutordoir <vd309@cam.ac.uk>
Requires-Dist: numpy
Requires-Dist: scipy
Project-URL: Source, https://github.com/vdutor/SphericalHarmonics
